pankaj_core42/__init__.py
pankaj_core42/example.py
pankaj_core42-0.0.1.dist-info/METADATA
pankaj_core42-0.0.1.dist-info/WHEEL
pankaj_core42-0.0.1.dist-info/top_level.txt
pankaj_core42-0.0.1.dist-info/RECORD
